README.md
bdeissct_dl/__init__.py
bdeissct_dl/bdeissct_model.py
bdeissct_dl/dl_model.py
bdeissct_dl/estimator.py
bdeissct_dl/model_serializer.py
bdeissct_dl/scaler_fitting.py
bdeissct_dl/sumstat_checker.py
bdeissct_dl/training.py
bdeissct_dl/tree_encoder.py
bdeissct_dl/tree_manager.py
bdext-0.1.71.dist-info/LICENSE
bdext-0.1.71.dist-info/METADATA
bdext-0.1.71.dist-info/WHEEL
bdext-0.1.71.dist-info/entry_points.txt
bdext-0.1.71.dist-info/top_level.txt
bdext-0.1.71.dist-info/RECORD
