Metadata-Version: 2.1
Name: bdext
Version: 0.1.71
Summary: Estimation of BDEISS-CT parameters from phylogenetic trees.
Home-page: https://github.com/modpath/bdeissct
Author: Anna Zhukova
Author-email: anna.zhukova@pasteur.fr
License: UNKNOWN
Keywords: phylogenetics,birth-death model,incubation,super-spreading,contact tracing
Platform: UNKNOWN
Classifier: Development Status :: 4 - Beta
Classifier: Environment :: Console
Classifier: Intended Audience :: Developers
Classifier: Topic :: Scientific/Engineering :: Bio-Informatics
Classifier: Topic :: Software Development
Classifier: Topic :: Software Development :: Libraries :: Python Modules
Requires-Dist: tensorflow==2.19.0
Requires-Dist: six
Requires-Dist: ete3
Requires-Dist: numpy==2.0.2
Requires-Dist: scipy==1.14.1
Requires-Dist: biopython
Requires-Dist: scikit-learn==1.5.2
Requires-Dist: pandas==2.2.3
Requires-Dist: treesumstats==0.7
